jupyterlab_s3_browser/__init__.py
jupyterlab_s3_browser/_version.py
jupyterlab_s3_browser/handlers.py
jupyterlab_s3_browser/labextension/package.json
jupyterlab_s3_browser/labextension/static/268.f31edca7f28c6bfffe28.js
jupyterlab_s3_browser/labextension/static/534.9645931ef1a95d5a9df1.js
jupyterlab_s3_browser/labextension/static/742.e2d83637b4dbb625a240.js
jupyterlab_s3_browser/labextension/static/remoteEntry.aa6024c5ea40b82c48e7.js
jupyterlab_s3_browser/labextension/static/style.js
jupyterlab_s3_browser/tests/__init__.py
jupyterlab_s3_browser/tests/test_auth.py
jupyterlab_s3_browser/tests/test_get_s3.py
jupyterlab_s3_browser_uccps/__init__.py
jupyterlab_s3_browser_uccps/_version.py
jupyterlab_s3_browser_uccps/handlers.py
jupyterlab_s3_browser_uccps/labextension/package.json
jupyterlab_s3_browser_uccps/labextension/static/268.9f7aa0158cdfda8baf56.js
jupyterlab_s3_browser_uccps/labextension/static/534.9645931ef1a95d5a9df1.js
jupyterlab_s3_browser_uccps/labextension/static/742.e2d83637b4dbb625a240.js
jupyterlab_s3_browser_uccps/labextension/static/remoteEntry.a9b108e22db5ac7c4504.js
jupyterlab_s3_browser_uccps/labextension/static/style.js
jupyterlab_s3_browser_uccps/tests/__init__.py
jupyterlab_s3_browser_uccps/tests/test_auth.py
jupyterlab_s3_browser_uccps/tests/test_get_s3.py
jupyterlab_s3_browser_uccps-0.10.5.data/data/share/jupyter/labextensions/jupyterlab-s3-browser-uccps/install.json
jupyterlab_s3_browser_uccps-0.10.5.data/data/share/jupyter/labextensions/jupyterlab-s3-browser-uccps/package.json
jupyterlab_s3_browser_uccps-0.10.5.data/data/share/jupyter/labextensions/jupyterlab-s3-browser-uccps/static/268.9f7aa0158cdfda8baf56.js
jupyterlab_s3_browser_uccps-0.10.5.data/data/share/jupyter/labextensions/jupyterlab-s3-browser-uccps/static/534.9645931ef1a95d5a9df1.js
jupyterlab_s3_browser_uccps-0.10.5.data/data/share/jupyter/labextensions/jupyterlab-s3-browser-uccps/static/742.e2d83637b4dbb625a240.js
jupyterlab_s3_browser_uccps-0.10.5.dist-info/LICENSE
jupyterlab_s3_browser_uccps-0.10.5.dist-info/METADATA
jupyterlab_s3_browser_uccps-0.10.5.dist-info/WHEEL
jupyterlab_s3_browser_uccps-0.10.5.dist-info/top_level.txt
jupyterlab_s3_browser_uccps-0.10.5.dist-info/RECORD
