Metadata-Version: 2.1
Name: jupyterlab-s3-browser-uccps
Version: 0.10.5
Summary: JupyterLab extension for browsing S3-compatible object storage
Home-page: https://github.com/IBM/jupyterlab_s3_browser
Author: James Reeve
License: Apache-2.0
Keywords: Jupyter,JupyterLab,JupyterLab3,S3
Platform: Linux
Platform: Mac OS X
Platform: Windows
Classifier: Intended Audience :: Developers
Classifier: Intended Audience :: Education
Classifier: Intended Audience :: Science/Research
Classifier: License :: OSI Approved :: Apache Software License
Classifier: Programming Language :: Python
Classifier: Programming Language :: Python :: 3
Classifier: Framework :: Jupyter
Requires-Python: >=3.6
License-File: LICENSE
Requires-Dist: notebook
Requires-Dist: boto3
Requires-Dist: jupyter-server
Requires-Dist: singleton-decorator
Requires-Dist: jupyterlab (>=2.0.0)
Provides-Extra: dev
Requires-Dist: jupyter-packaging (~=0.7.9) ; extra == 'dev'
Requires-Dist: pytest ; extra == 'dev'
Requires-Dist: moto ; extra == 'dev'
Requires-Dist: coverage ; extra == 'dev'
